xarray_sentinel/__init__.py
xarray_sentinel/conventions.py
xarray_sentinel/esa_safe.py
xarray_sentinel/py.typed
xarray_sentinel/reformat.py
xarray_sentinel/sentinel1.py
xarray_sentinel/version.py
xarray_sentinel/xarray_backends.py
xarray_sentinel/resources/sentinel1/my-gml.xsd
xarray_sentinel/resources/sentinel1/my-no-namespace.xsd
xarray_sentinel/resources/sentinel1/my-safe-sentinel-1.0-sentinel-1-sar-level-1.xsd
xarray_sentinel/resources/sentinel1/my-safe-sentinel-1.0-sentinel-1.xsd
xarray_sentinel/resources/sentinel1/my-safe-sentinel-1.0.xsd
xarray_sentinel/resources/sentinel1/my-schema_orb.xsd
xarray_sentinel/resources/sentinel1/my-xfdu.xsd
xarray_sentinel/resources/sentinel1/s1-level-1-calibration.xsd
xarray_sentinel/resources/sentinel1/s1-level-1-noise.xsd
xarray_sentinel/resources/sentinel1/s1-level-1-product.xsd
xarray_sentinel/resources/sentinel1/s1-level-1-rfi.xsd
xarray_sentinel/resources/sentinel1/s1-object-types.xsd
xarray_sentinel-0.9.5.dist-info/LICENSE
xarray_sentinel-0.9.5.dist-info/METADATA
xarray_sentinel-0.9.5.dist-info/WHEEL
xarray_sentinel-0.9.5.dist-info/entry_points.txt
xarray_sentinel-0.9.5.dist-info/top_level.txt
xarray_sentinel-0.9.5.dist-info/RECORD
