Metadata-Version: 2.1
Name: xarray-sentinel
Version: 0.9.5
Summary: Easily access and explore the SAR data products of the Copernicus Sentinel-1 satellite mission
Home-page: https://github.com/bopen/xarray-sentinel
Author: B-Open
Author-email: software@bopen.eu
License: Apache License 2.0
Keywords: copernicus,earth-observation,radar,remote-sensing,satellite-imagery,sentinel-1,sar,synthetic-aperture-radar,xarray
Classifier: Development Status :: 4 - Beta
Classifier: Intended Audience :: Science/Research
Classifier: License :: OSI Approved :: Apache Software License
Classifier: Operating System :: OS Independent
Classifier: Programming Language :: Python
Classifier: Programming Language :: Python :: 3
Classifier: Programming Language :: Python :: 3.8
Classifier: Programming Language :: Python :: 3.9
Classifier: Programming Language :: Python :: 3.10
Classifier: Topic :: Scientific/Engineering
Requires-Python: >=3.8
License-File: LICENSE
Requires-Dist: fsspec
Requires-Dist: numpy
Requires-Dist: pandas
Requires-Dist: rioxarray
Requires-Dist: xarray (>=0.18.0)
Requires-Dist: xmlschema
